[
  {
    "day": "Nov 19, 2023",
    "sold": 2
  },
  {
    "day": "Nov 20, 2023",
    "sold": 0
  },
  {
    "day": "Nov 22, 2023",
    "sold": 3
  },
  {
    "day": "Nov 26, 2023",
    "sold": 0
  },
  {
    "day": "Nov 27, 2023",
    "sold": 7
  },
  {
    "day": "Dec 2, 2023",
    "sold": 15
  },
  {
    "day": "Dec 14, 2023",
    "sold": 40
  },
  {
    "day": "Dec 15, 2023",
    "sold": 50
  },
  {
    "day": "Dec 16, 2023",
    "sold": 55
  },
  {
    "day": "Dec 17, 2023",
    "sold": 95
  },
 
  {
    "day": "Jan 16, 2024",
    "sold": 122
  },
  {
    "day": "Jan 17, 2024",
    "sold": 111
  },
  {
    "day": "Jan 21, 2024",
    "sold": 111
  },
  {
    "day": "Jan 22, 2024",
    "sold": 120
  },
  {
    "day": "Jan 23, 2024",
    "sold": 133
  },
  {
    "day": "Jan 24, 2024",
    "sold": 140
  },
  {
    "day": "Jan 26, 2024",
    "sold": 70
  },
  {
    "day": "Jan 27, 2024",
    "sold": 100
  },

  {
    "day": "Jan 29, 2024",
    "sold": 133
  },
  {
    "day": "Jan 30, 2024",
    "sold": 144
  },
  {
    "day": "Jan 31, 2024",
    "sold": 153
  },
  {
    "day": "Feb 4, 2024",
    "sold": 150
  },
 
  {
    "day": "Feb 6, 2024",
    "sold": 150
  },
  {
    "day": "Feb 7, 2024",
    "sold": 155
  },
 
  {
    "day": "Feb 9, 2024",
    "sold": 165
  },
  {
    "day": "Feb 10, 2024",
    "sold": 170
  },

  {
    "day": "Feb 12, 2024",
    "sold": 165
  },
  {
    "day": "Feb 13, 2024",
    "sold": 160
  },
  {
    "day": "Feb 14, 2024",
    "sold": 150
  },

  {
    "day": "Feb 16, 2024",
    "sold": 180
  },
  {
    "day": "Feb 17, 2024",
    "sold": 100
  },

  {
    "day": "Feb 19, 2024",
    "sold": 120
  },
  {
    "day": "Feb 20, 2024",
    "sold": 144
  },
  {
    "day": "Feb 21, 2024",
    "sold": 150
  },
  {
    "day": "Feb 22, 2024",
    "sold": 165
  },
  {
    "day": "Feb 23, 2024",
    "sold": 185
  },
  {
    "day": "Feb 24, 2024",
    "sold": 200
  }
]